seeq/data_lab_env_mgr/__init__.py
seeq/data_lab_env_mgr/_dlem.py
seeq/data_lab_env_mgr/_helper.py
seeq/data_lab_env_mgr/_mixpanel.py
seeq/data_lab_env_mgr/_schedule.py
seeq/data_lab_env_mgr/_version.py
seeq/data_lab_env_mgr/notebooks/data_lab_env_mgr_scheduled_job.ipynb
seeq_data_lab_env_mgr-0.6.0.dist-info/licenses/LICENSE
seeq_data_lab_env_mgr-0.6.0.dist-info/METADATA
seeq_data_lab_env_mgr-0.6.0.dist-info/WHEEL
seeq_data_lab_env_mgr-0.6.0.dist-info/top_level.txt
seeq_data_lab_env_mgr-0.6.0.dist-info/RECORD
