Metadata-Version: 2.4
Name: seeq-data-lab-env-mgr
Version: 0.6.0
Summary: Data Lab Environment Manager
Home-page: https://github.com/seeq12/seeq-data-lab-env-mgr
Author: Seeq Corporation
Author-email: support@seeq.com
Classifier: Programming Language :: Python :: 3
Classifier: License :: OSI Approved :: MIT License
Classifier: Operating System :: OS Independent
Requires-Python: >=3.8
License-File: LICENSE
Requires-Dist: ipywidgets>=7.7.0
Requires-Dist: ipython>=8.1.0
Requires-Dist: mixpanel>=4.10.0
Requires-Dist: nbformat>=5.4.0
Requires-Dist: pandas>=1.5.0
Requires-Dist: requests
Requires-Dist: seeq
Requires-Dist: seeq-spy
Dynamic: author
Dynamic: author-email
Dynamic: classifier
Dynamic: description
Dynamic: description-content-type
Dynamic: home-page
Dynamic: license-file
Dynamic: requires-dist
Dynamic: requires-python
Dynamic: summary
